madoc/__init__.py
madoc/base64_converter.py
madoc/loader.py
madoc/madoc_recursive.py
madoc/main.py
madoc/assets/__init__.py
madoc/assets/favicon.ico
madoc/silly_engine/__init__.py
madoc/silly_engine/logger.py
madoc/silly_engine/text_tools.py
madoc/templates/__init__.py
madoc/templates/madoc/__init__.py
madoc/templates/madoc/_recursive_menu.html
madoc/templates/madoc/logo64.html
madoc/templates/madoc/madoc_style.css
madoc/templates/madoc/pygments.css
madoc/templates/madoc/recursive_index.html
madoc/templates/madoc/recursive_render.html
madoc/templates/madoc/render.html
madoc/templates/madoc/xrender.html
madoc-1.2.5.dist-info/licenses/LICENSE.md
madoc-1.2.5.dist-info/METADATA
madoc-1.2.5.dist-info/WHEEL
madoc-1.2.5.dist-info/entry_points.txt
madoc-1.2.5.dist-info/top_level.txt
madoc-1.2.5.dist-info/RECORD
