Metadata-Version: 2.4
Name: madoc
Version: 1.2.5
Summary: Documentation generator from markdown files
Author-email: Vincent Fabre <peigne.plume@gmail.com>
License-Expression: MIT
Project-URL: Homepage, https://github.com/byoso/madoc
Project-URL: Repository, https://github.com/byoso/madoc
Keywords: markdown,html,documentation
Classifier: Programming Language :: Python :: 3
Classifier: Development Status :: 5 - Production/Stable
Classifier: Natural Language :: English
Requires-Python: >=3.8
License-File: LICENSE.md
Requires-Dist: jinja2<4.0.0,>=3.1.2
Requires-Dist: markdown<4.0.0,>=3.7
Requires-Dist: pygments<3.0.0,>=2.19.1
Requires-Dist: requests<3.0.0,>=2.32.3
Dynamic: license-file
